tackle/__init__.py
tackle/cli.py
tackle/exceptions.py
tackle/hooks.py
tackle/macros.py
tackle/main.py
tackle/models.py
tackle/parser.py
tackle/render.py
tackle/settings.py
tackle/special_vars.py
tackle/providers/.gitignore
tackle/providers/__init__.py
tackle/providers/collections/.tackle.meta.yaml
tackle/providers/collections/notes.md
tackle/providers/collections/hooks/concatenate.py
tackle/providers/collections/hooks/distinct.py
tackle/providers/collections/hooks/list_key.py
tackle/providers/collections/hooks/map_to_list_key_values.py
tackle/providers/collections/hooks/sort.py
tackle/providers/collections/tests/concatenate.yaml
tackle/providers/collections/tests/distinct.yaml
tackle/providers/collections/tests/list-keys.yaml
tackle/providers/collections/tests/sort-in-place.yaml
tackle/providers/collections/tests/sort-map.yaml
tackle/providers/collections/tests/test_provider_collections.py
tackle/providers/command/.tackle.meta.yaml
tackle/providers/command/hooks/command.py
tackle/providers/command/hooks/system.py
tackle/providers/command/tests/exit-ignore.yaml
tackle/providers/command/tests/exit-long.yaml
tackle/providers/command/tests/exit.yaml
tackle/providers/command/tests/interactive.yaml
tackle/providers/command/tests/list-dir.yaml
tackle/providers/command/tests/multi-line-cmd.yaml
tackle/providers/command/tests/test_provider_command.py
tackle/providers/console/.tackle.meta.yaml
tackle/providers/console/requirements.txt
tackle/providers/console/scratch.py
tackle/providers/console/hooks/__init__.py
tackle/providers/console/hooks/markdown.py
tackle/providers/console/hooks/prints.py
tackle/providers/console/hooks/table.py
tackle/providers/console/tests/markdown.yaml
tackle/providers/console/tests/pprint.yaml
tackle/providers/console/tests/print.yaml
tackle/providers/console/tests/table.yaml
tackle/providers/console/tests/table_split.yaml
tackle/providers/console/tests/test_provider_console_print.py
tackle/providers/console/tests/test_provider_console_rich.py
tackle_box-0.4.1.dist-info/LICENSE
tackle_box-0.4.1.dist-info/METADATA
tackle_box-0.4.1.dist-info/WHEEL
tackle_box-0.4.1.dist-info/entry_points.txt
tackle_box-0.4.1.dist-info/top_level.txt
tackle_box-0.4.1.dist-info/RECORD
