Metadata-Version: 2.1
Name: tackle-box
Version: 0.4.1
Summary: Tackle box is a declarative DSL for building modular workflows and code generators. Tool is plugins based and can easily be extended by writing additional hooks or importing external providers creating a web of interoperable CLIs.
Home-page: https://github.com/robcxyz/tackle-box
Author: Rob Cannon
Author-email: robc.io.opensource@gmail.com
License: BSD
Keywords: cookiecutter,tackle,tackle-box,tacklebox,tackle box,Python,projects,project templates,Jinja2,skeleton,scaffolding,project directory,package,packaging,kubernetes
Platform: UNKNOWN
Classifier: Development Status :: 5 - Production/Stable
Classifier: Environment :: Console
Classifier: Intended Audience :: Developers
Classifier: Natural Language :: English
Classifier: License :: OSI Approved :: BSD License
Classifier: Programming Language :: Python :: 3 :: Only
Classifier: Programming Language :: Python :: 3
Classifier: Programming Language :: Python :: 3.7
Classifier: Programming Language :: Python :: 3.8
Classifier: Programming Language :: Python :: 3.9
Classifier: Programming Language :: Python :: 3.10
Classifier: Programming Language :: Python :: Implementation :: CPython
Classifier: Programming Language :: Python :: Implementation :: PyPy
Classifier: Programming Language :: Python
Classifier: Topic :: Software Development
Requires-Python: >=3.7
License-File: LICENSE
Requires-Dist: InquirerPy (>=0.3.3)
Requires-Dist: Jinja2 (>3.0.0)
Requires-Dist: pydantic (>=1.8.0)
Requires-Dist: rich (>=12.6.0)
Requires-Dist: ruamel.yaml (>=0.17.0)
Requires-Dist: xdg (==5.1.1)
Provides-Extra: all
Requires-Dist: GitPython ; extra == 'all'
Requires-Dist: flake8 ; extra == 'all'
Requires-Dist: freezegun ; extra == 'all'
Requires-Dist: kubernetes ; extra == 'all'
Requires-Dist: paramiko ; extra == 'all'
Requires-Dist: psycopg2-binary ; extra == 'all'
Requires-Dist: ptyprocess ; extra == 'all'
Requires-Dist: pytest ; extra == 'all'
Requires-Dist: pytest-asyncio ; extra == 'all'
Requires-Dist: pytest-cov ; extra == 'all'
Requires-Dist: pytest-mock ; extra == 'all'
Requires-Dist: requests ; extra == 'all'
Requires-Dist: rich ; extra == 'all'
Requires-Dist: toml (>=0.10.0) ; extra == 'all'
Requires-Dist: tox ; extra == 'all'
Provides-Extra: console
Requires-Dist: rich ; extra == 'console'
Provides-Extra: dev
Requires-Dist: flake8 ; extra == 'dev'
Requires-Dist: freezegun ; extra == 'dev'
Requires-Dist: ptyprocess ; extra == 'dev'
Requires-Dist: pytest ; extra == 'dev'
Requires-Dist: pytest-asyncio ; extra == 'dev'
Requires-Dist: pytest-cov ; extra == 'dev'
Requires-Dist: pytest-mock ; extra == 'dev'
Requires-Dist: requests ; extra == 'dev'
Requires-Dist: tox ; extra == 'dev'
Provides-Extra: git
Requires-Dist: GitPython ; extra == 'git'
Provides-Extra: kubernetes
Requires-Dist: kubernetes ; extra == 'kubernetes'
Provides-Extra: postgres
Requires-Dist: psycopg2-binary ; extra == 'postgres'
Provides-Extra: ssh
Requires-Dist: paramiko ; extra == 'ssh'
Provides-Extra: toml
Requires-Dist: toml (>=0.10.0) ; extra == 'toml'
Provides-Extra: web
Requires-Dist: requests ; extra == 'web'
